{
  "Blue": {
    "tt_glb_color_blue_100": {
      "value": "#f3f9fd",
      "type": "color",
      "parent": "1 | Global/Colours/HEXs",
      "description": ""
    },
    "tt_glb_color_blue_200": {
      "value": "#dfeef8",
      "type": "color",
      "parent": "1 | Global/Colours/HEXs",
      "description": ""
    },
    "tt_glb_color_blue_300": {
      "value": "#8dc3eb",
      "type": "color",
      "parent": "1 | Global/Colours/HEXs",
      "description": ""
    },
    "tt_glb_color_blue_400": {
      "value": "#1988cf",
      "type": "color",
      "parent": "1 | Global/Colours/HEXs",
      "description": ""
    },
    "tt_glb_color_blue_500": {
      "value": "#105287",
      "type": "color",
      "parent": "1 | Global/Colours/HEXs",
      "description": ""
    }
  },
  "Grey": {
    "tt_glb_color_grey_100": {
      "value": "#f4f5f6",
      "type": "color",
      "parent": "1 | Global/Colours/HEXs",
      "description": ""
    },
    "tt_glb_color_grey_150": {
      "value": "#ECECEC",
      "type": "color",
      "parent": "1 | Global/Colours/HEXs"
    },
    "tt_glb_color_grey_200": {
      "value": "#d8dadd",
      "type": "color",
      "parent": "1 | Global/Colours/HEXs",
      "description": ""
    },
    "tt_glb_color_grey_300": {
      "value": "#abafb3",
      "type": "color",
      "parent": "1 | Global/Colours/HEXs",
      "description": ""
    },
    "tt_glb_color_grey_400": {
      "value": "#727c85",
      "type": "color",
      "parent": "1 | Global/Colours/HEXs",
      "description": ""
    },
    "tt_glb_color_grey_500": {
      "value": "#3c4956",
      "type": "color",
      "parent": "1 | Global/Colours/HEXs",
      "description": ""
    },
    "tt_glb_color_grey_600": {
      "value": "#202C37",
      "type": "color",
      "parent": "1 | Global/Colours/HEXs"
    },
    "tt_glb_color_grey_700": {
      "value": "#18212a",
      "type": "color",
      "parent": "1 | Global/Colours/HEXs"
    },
    "tt_glb_color_grey_800": {
      "value": "#11181e",
      "type": "color",
      "parent": "1 | Global/Colours/HEXs",
      "description": ""
    },
    "tt_glb_color_grey_800_a8": {
      "value": "#11181ecc",
      "type": "color",
      "parent": "1 | Global/Colours/HEXs",
      "description": ""
    },
    "tt_glb_color_grey_900": {
      "value": "#0a0e11",
      "type": "color",
      "parent": "1 | Global/Colours/HEXs",
      "description": ""
    }
  },
  "Black&White": {
    "tt_glb_color_white": {
      "value": "#ffffff",
      "type": "color",
      "parent": "1 | Global/Colours/HEXs",
      "description": ""
    },
    "tt_glb_color_white_a8": {
      "value": "#ffffffcc",
      "type": "color",
      "parent": "1 | Global/Colours/HEXs",
      "description": ""
    },
    "tt_glb_color_white_a15": {
      "value": "rgba(255,255,255,0.15)",
      "type": "color",
      "parent": "1 | Global/Colours/HEXs"
    },
    "tt_glb_color_black": {
      "value": "#000000",
      "type": "color",
      "parent": "1 | Global/Colours/HEXs",
      "description": ""
    },
    "tt_glb_color_black_a3": {
      "value": "#0000004d",
      "type": "color",
      "parent": "1 | Global/Colours/HEXs",
      "description": ""
    },
    "tt_glb_color_black_a5": {
      "value": "#0000007F",
      "type": "color",
      "parent": "1 | Global/Colours/HEXs"
    },
    "tt_glb_color_black_a15": {
      "value": "rgba(0,0,0,0.15)",
      "type": "color",
      "parent": "1 | Global/Colours/HEXs"
    },
    "tt_glb_color_black_a8": {
      "value": "#000000cc",
      "type": "color",
      "parent": "1 | Global/Colours/HEXs",
      "description": ""
    },
    "tt_glb_color_null": {
      "value": "#ffffff00",
      "type": "color",
      "parent": "1 | Global/Colours/HEXs",
      "description": ""
    }
  },
  "Green": {
    "tt_glb_color_green_100": {
      "value": "#9ce0c4",
      "type": "color",
      "parent": "1 | Global/Colours/HEXs",
      "description": ""
    },
    "tt_glb_color_green_200": {
      "value": "#39c189",
      "type": "color",
      "parent": "1 | Global/Colours/HEXs",
      "description": ""
    },
    "tt_glb_color_green_300": {
      "value": "#039357",
      "type": "color",
      "parent": "1 | Global/Colours/HEXs",
      "description": ""
    },
    "tt_glb_color_green_300_a4": {
      "value": "rgba(3,147,87,0.4)",
      "type": "color",
      "parent": "1 | Global/Colours/HEXs"
    }
  },
  "Red": {
    "tt_glb_color_red_100": {
      "value": "#f84545",
      "type": "color",
      "parent": "1 | Global/Colours/HEXs"
    },
    "tt_glb_color_red_200": {
      "value": "#b82626",
      "type": "color",
      "parent": "1 | Global/Colours/HEXs"
    },
    "tt_glb_color_red_300": {
      "value": "#8d0000",
      "type": "color",
      "parent": "1 | Global/Colours/HEXs"
    },
    "tt_glb_color_red_300_a4": {
      "value": "rgba(141,0,0,0.4)",
      "type": "color",
      "parent": "1 | Global/Colours/HEXs"
    }
  },
  "Orange": {
    "tt_glb_color_orange_100": {
      "value": "#fdc19d",
      "type": "color",
      "parent": "1 | Global/Colours/HEXs",
      "description": ""
    },
    "tt_glb_color_orange_200": {
      "value": "#fc823a",
      "type": "color",
      "parent": "1 | Global/Colours/HEXs",
      "description": ""
    },
    "tt_glb_color_orange_300": {
      "value": "#c44d07",
      "type": "color",
      "parent": "1 | Global/Colours/HEXs",
      "description": ""
    },
    "tt_glb_color_orange_300_a4": {
      "value": "#c44d07",
      "type": "color",
      "parent": "1 | Global/Colours/HEXs"
    }
  },
  "Yellow": {
    "tt_glb_color_yellow_100": {
      "value": "#f5a623",
      "type": "color",
      "parent": "1 | Global/Colours/HEXs"
    },
    "tt_glb_color_yellow_200": {
      "value": "#bf811b",
      "type": "color",
      "parent": "1 | Global/Colours/HEXs"
    },
    "tt_glb_color_yellow_300": {
      "value": "#936415",
      "type": "color",
      "parent": "1 | Global/Colours/HEXs"
    },
    "tt_glb_color_yellow_300_a4": {
      "value": "rgba(147,100,21,0.4)",
      "type": "color",
      "parent": "1 | Global/Colours/HEXs"
    }
  },
  "Localised": {
    "tt_glb_color_usaGreen_100": {
      "value": "#72A195",
      "type": "color",
      "parent": "1 | Global/Colours/HEXs"
    },
    "tt_glb_color_usaGreen_200": {
      "value": "#00664B",
      "type": "color",
      "parent": "1 | Global/Colours/HEXs"
    },
    "tt_glb_color_usaGreen_300": {
      "value": "#004231",
      "type": "color",
      "parent": "1 | Global/Colours/HEXs"
    },
    "tt_glb_color_euBlue_100": {
      "value": "#2f598e",
      "type": "color",
      "parent": "1 | Global/Colours/HEXs",
      "description": ""
    },
    "tt_glb_color_euBlue_200": {
      "value": "#163f74",
      "type": "color",
      "parent": "1 | Global/Colours/HEXs",
      "description": ""
    },
    "tt_glb_color_euBlue_300": {
      "value": "#11315a",
      "type": "color",
      "parent": "1 | Global/Colours/HEXs",
      "description": ""
    }
  },
  "Extended Colour Collection": {
    "tt_glb_color_azure_100": {
      "value": "#2baeff",
      "type": "color",
      "parent": "1 | Global/Colours/HEXs",
      "description": ""
    },
    "tt_glb_color_azure_200": {
      "value": "#0e7ec3",
      "type": "color",
      "parent": "1 | Global/Colours/HEXs",
      "description": ""
    },
    "tt_glb_color_cobalt_100": {
      "value": "#2d81c6",
      "type": "color",
      "parent": "1 | Global/Colours/HEXs",
      "description": ""
    },
    "tt_glb_color_cobalt_200": {
      "value": "#276293",
      "type": "color",
      "parent": "1 | Global/Colours/HEXs",
      "description": ""
    },
    "tt_glb_color_lavender_100": {
      "value": "#9088da",
      "type": "color",
      "parent": "1 | Global/Colours/HEXs",
      "description": ""
    },
    "tt_glb_color_lavender_200": {
      "value": "#6a61be",
      "type": "color",
      "parent": "1 | Global/Colours/HEXs",
      "description": ""
    },
    "tt_glb_color_periwinkle_100": {
      "value": "#9496b4",
      "type": "color",
      "parent": "1 | Global/Colours/HEXs",
      "description": ""
    },
    "tt_glb_color_periwinkle_200": {
      "value": "#757690",
      "type": "color",
      "parent": "1 | Global/Colours/HEXs",
      "description": ""
    },
    "tt_glb_color_orchid_100": {
      "value": "#c272d0",
      "type": "color",
      "parent": "1 | Global/Colours/HEXs",
      "description": ""
    },
    "tt_glb_color_orchid_200": {
      "value": "#a34eb2",
      "type": "color",
      "parent": "1 | Global/Colours/HEXs",
      "description": ""
    },
    "tt_glb_color_wayfarer_100": {
      "value": "#ed73be",
      "type": "color",
      "parent": "1 | Global/Colours/HEXs",
      "description": ""
    },
    "tt_glb_color_wayfarer_200": {
      "value": "#c7529a",
      "type": "color",
      "parent": "1 | Global/Colours/HEXs",
      "description": ""
    },
    "tt_glb_color_coral_100": {
      "value": "#e6655a",
      "type": "color",
      "parent": "1 | Global/Colours/HEXs",
      "description": ""
    },
    "tt_glb_color_coral_200": {
      "value": "#bf544b",
      "type": "color",
      "parent": "1 | Global/Colours/HEXs",
      "description": ""
    },
    "tt_glb_color_tangerine_100": {
      "value": "#f08a3f",
      "type": "color",
      "parent": "1 | Global/Colours/HEXs",
      "description": ""
    },
    "tt_glb_color_tangerine_200": {
      "value": "#ce6213",
      "type": "color",
      "parent": "1 | Global/Colours/HEXs",
      "description": ""
    },
    "tt_glb_color_granite_100": {
      "value": "#a9909e",
      "type": "color",
      "parent": "1 | Global/Colours/HEXs",
      "description": ""
    },
    "tt_glb_color_granite_200": {
      "value": "#87727e",
      "type": "color",
      "parent": "1 | Global/Colours/HEXs",
      "description": ""
    },
    "tt_glb_color_driftwood_100": {
      "value": "#beb2a2",
      "type": "color",
      "parent": "1 | Global/Colours/HEXs",
      "description": ""
    },
    "tt_glb_color_driftwood_200": {
      "value": "#958c81",
      "type": "color",
      "parent": "1 | Global/Colours/HEXs",
      "description": ""
    },
    "tt_glb_color_silverstone_100": {
      "value": "#999a9b",
      "type": "color",
      "parent": "1 | Global/Colours/HEXs",
      "description": ""
    },
    "tt_glb_color_silverstone_200": {
      "value": "#797979",
      "type": "color",
      "parent": "1 | Global/Colours/HEXs",
      "description": ""
    },
    "tt_glb_color_teal_100": {
      "value": "#1fb18e",
      "type": "color",
      "parent": "1 | Global/Colours/HEXs",
      "description": ""
    },
    "tt_glb_color_teal_200": {
      "value": "#1b9175",
      "type": "color",
      "parent": "1 | Global/Colours/HEXs",
      "description": ""
    },
    "tt_glb_color_evergreen_100": {
      "value": "#08b063",
      "type": "color",
      "parent": "1 | Global/Colours/HEXs",
      "description": ""
    },
    "tt_glb_color_evergreen_200": {
      "value": "#0d9061",
      "type": "color",
      "parent": "1 | Global/Colours/HEXs",
      "description": ""
    }
  },
  "Figma Only": {
    "Blossom_100": {
      "value": "#ff2f92",
      "type": "color",
      "parent": "1 | Global/Colours/HEXs",
      "description": ""
    },
    "tt_glb_color_grey_800_a5": {
      "value": "#11181e80",
      "type": "color",
      "parent": "1 | Global/Colours/HEXs",
      "description": ""
    },
    "tt_glb_color_white_a5": {
      "value": "#ffffff80",
      "type": "color",
      "parent": "1 | Global/Colours/HEXs",
      "description": ""
    }
  },
  "EV Tones": {
    "Mint": {
      "tt_glb_color_mint_100": {
        "value": "#81dfca",
        "type": "color",
        "parent": "1 | Global/Colours/HEXs",
        "description": ""
      },
      "tt_glb_color_mint_200": {
        "value": "#4fd2b5",
        "type": "color",
        "parent": "1 | Global/Colours/HEXs",
        "description": ""
      },
      "tt_glb_color_mint_300": {
        "value": "#03bf95",
        "type": "color",
        "parent": "1 | Global/Colours/HEXs",
        "description": ""
      },
      "tt_glb_color_mint_400": {
        "value": "#027c61",
        "type": "color",
        "parent": "1 | Global/Colours/HEXs",
        "description": ""
      },
      "tt_glb_color_mint_500": {
        "value": "#02604b",
        "type": "color",
        "parent": "1 | Global/Colours/HEXs",
        "description": ""
      }
    }
  },
  "Blueprint": {
    "Blueprint_100": {
      "value": "#ebf2ff",
      "type": "color",
      "parent": "1 | Global/Colours/HEXs",
      "description": ""
    },
    "Blueprint_200": {
      "value": "#e6efff",
      "type": "color",
      "parent": "1 | Global/Colours/HEXs",
      "description": ""
    },
    "Blueprint_300": {
      "value": "#ccdfff",
      "type": "color",
      "parent": "1 | Global/Colours/HEXs",
      "description": ""
    },
    "Blueprint_400": {
      "value": "#80b0ff",
      "type": "color",
      "parent": "1 | Global/Colours/HEXs",
      "description": ""
    },
    "Blueprint_500": {
      "value": "#0060ff",
      "type": "color",
      "parent": "1 | Global/Colours/HEXs",
      "description": ""
    }
  }
}